<?xml version="1.0" encoding="UTF-8"?>
<beans xmlns="http://www.springframework.org/schema/beans"
	xmlns:xsi="http://www.w3.org/2001/XMLSchema-instance" xmlns:mvc="http://www.springframework.org/schema/mvc"
	xmlns:p="http://www.springframework.org/schema/p" xmlns:context="http://www.springframework.org/schema/context"
	xmlns:aop="http://www.springframework.org/schema/aop"
	xsi:schemaLocation="
	 http://www.springframework.org/schema/beans
	 http://www.springframework.org/schema/beans/spring-beans.xsd
	 http://www.springframework.org/schema/mvc
	 http://www.springframework.org/schema/mvc/spring-mvc.xsd
	 http://www.springframework.org/schema/context
	 http://www.springframework.org/schema/context/spring-context.xsd
	 http://www.springframework.org/schema/aop 
	 http://www.springframework.org/schema/aop/spring-aop-4.0.xsd">

	<context:property-placeholder location="classpath:resources/app.properties" />

	<mvc:view-controller path="/error" view-name="error/500" />
	<mvc:resources mapping="/favicon.ico" location="/static/img/favicon.ico" />

	<bean id="multipartResolver"
		class="org.springframework.web.multipart.commons.CommonsMultipartResolver">
		<property name="maxUploadSize" value="${app.uploadLimitSize}" />
		<property name="maxInMemorySize" value="1024" />
	</bean>

	<mvc:resources location="/static/" mapping="/static/**"
		cache-period="31556926" />

	<!-- 包扫描 -->
	<context:component-scan base-package="me.qyh.blog.web.controller" />

	<bean class="me.qyh.blog.ui.TplRender" />

	<bean class="org.thymeleaf.spring4.view.ThymeleafViewResolver">
		<property name="contentType" value="text/html" />
		<property name="characterEncoding" value="utf-8" />
		<property name="templateEngine" ref="templateEngine" />
		<property name="viewClass" value="me.qyh.blog.ui._ThymeleafView" />
	</bean>

	<mvc:annotation-driven>
		<mvc:message-converters register-defaults="true">
			<bean
				class="org.springframework.http.converter.json.MappingJackson2HttpMessageConverter">
				<property name="objectMapper" value="#{T(me.qyh.util.Jsons).getMapper()}" />
			</bean>
		</mvc:message-converters>
		<mvc:argument-resolvers>
			<bean class="me.qyh.blog.lock.LockArgumentResolver" />
		</mvc:argument-resolvers>
		<mvc:return-value-handlers>
			<bean class="me.qyh.blog.web.controller.PageReturnMethodReturnValueHandler" />
		</mvc:return-value-handlers>
	</mvc:annotation-driven>

	<bean class="me.qyh.blog.file.local.LocalResourceSimpleUrlHandlerMapping" />

	<bean id="annotationHandlerMapping"
		class="org.springframework.web.servlet.mvc.annotation.DefaultAnnotationHandlerMapping">
		<property name="order" value="1" />
		<property name="alwaysUseFullPath" value="true" />
	</bean>

	<!-- csrf token store stragey -->
	<bean class="me.qyh.blog.security.csrf.HttpSessionCsrfTokenRepository" />

	<mvc:interceptors>
		<mvc:interceptor>
			<mvc:mapping path="/**" />
			<bean class="me.qyh.blog.web.interceptor.AppInterceptor" />
		</mvc:interceptor>
	</mvc:interceptors>

	<!-- 页面拓展 -->
	<bean class="me.qyh.blog.ui.page.ExpanedPageHandlerMapping" />
	<bean class="me.qyh.blog.ui.page.ExpandedPageRequestController" />


	<bean id="templateResolver" class="me.qyh.blog.ui.TplResolver">
		<property name="prefix" value="/WEB-INF/templates/" />
		<property name="suffix" value=".html" />
		<property name="templateMode" value="HTML" />
		<property name="characterEncoding" value="utf-8" />
	</bean>

	<bean id="templateEngine" class="me.qyh.blog.ui.UITemplateEngine">
		<property name="templateResolver" ref="templateResolver" />
	</bean>
	<bean class="me.qyh.blog.metaweblog.MetaweblogController">
		<property name="invalidIpMonitor">
			<bean class="me.qyh.blog.security.InvalidCountMonitor">
				<constructor-arg index="0" value="20" />
				<constructor-arg index="1" value="5" />
				<constructor-arg index="2" value="300" />
				<constructor-arg index="3" value="600" />
				<constructor-arg index="4" value="600" />
			</bean>
		</property>
	</bean>


	<!-- 默认评论服务 -->
	<bean class="me.qyh.blog.comment.CommentController" />
	<bean class="me.qyh.blog.comment.CommentMgrController" />
</beans>